ArangoPy-0.5.7.dist-info/METADATA
ArangoPy-0.5.7.dist-info/RECORD
ArangoPy-0.5.7.dist-info/WHEEL
ArangoPy-0.5.7.dist-info/top_level.txt
arangodb/__init__.py
arangodb/api.py
arangodb/six.py
arangodb/tests.py
arangodb/user.py
arangodb/index/__init__.py
arangodb/index/api.py
arangodb/index/general.py
arangodb/index/unique.py
arangodb/orm/__init__.py
arangodb/orm/fields.py
arangodb/orm/models.py
arangodb/query/__init__.py
arangodb/query/advanced.py
arangodb/query/simple.py
arangodb/query/utils/__init__.py
arangodb/query/utils/document.py
arangodb/server/__init__.py
arangodb/server/endpoint.py
arangodb/tests/__init__.py
arangodb/tests/base.py
arangodb/tests/endpoint.py
arangodb/tests/index.py
arangodb/tests/transaction.py
arangodb/tests/user.py
arangodb/tests/api/__init__.py
arangodb/tests/api/collection.py
arangodb/tests/api/database.py
arangodb/tests/api/document.py
arangodb/tests/orm/__init__.py
arangodb/tests/orm/manager_with_index.py
arangodb/tests/orm/model.py
arangodb/tests/orm/model_foreignkey.py
arangodb/tests/orm/model_manager.py
arangodb/tests/orm/fields/__init__.py
arangodb/tests/orm/fields/boolean_field.py
arangodb/tests/orm/fields/char_field.py
arangodb/tests/orm/fields/choice.py
arangodb/tests/orm/fields/date_field.py
arangodb/tests/orm/fields/datetime_field.py
arangodb/tests/orm/fields/dict_field.py
arangodb/tests/orm/fields/foreignkey.py
arangodb/tests/orm/fields/list_field.py
arangodb/tests/orm/fields/manytomany.py
arangodb/tests/orm/fields/number.py
arangodb/tests/orm/fields/uuid_field.py
arangodb/tests/query/__init__.py
arangodb/tests/query/advanced.py
arangodb/tests/query/aql.py
arangodb/tests/query/basic.py
arangodb/tests/query/escaping.py
arangodb/tests/query/index.py
arangodb/transaction/__init__.py
arangodb/transaction/action.py
arangodb/transaction/api.py
arangodb/transaction/controller.py
arangodb/transaction/javascript/__init__.py
arangodb/transaction/javascript/code.py
