Metadata-Version: 2.1
Name: ArangoPy
Version: 0.5.7
Summary: Driver for ArangoDB
Home-page: https://github.com/saeschdivara/ArangoPy
Author: saskyrardisaskyr
Author-email: saeschdivara@gmail.com
License: MIT
Platform: UNKNOWN
Requires: slumber
